odoo/addons/stock_valuation_layer_inventory_filter/README.rst
odoo/addons/stock_valuation_layer_inventory_filter/__init__.py
odoo/addons/stock_valuation_layer_inventory_filter/__manifest__.py
odoo/addons/stock_valuation_layer_inventory_filter/i18n/es.po
odoo/addons/stock_valuation_layer_inventory_filter/i18n/it.po
odoo/addons/stock_valuation_layer_inventory_filter/i18n/stock_valuation_layer_inventory_filter.pot
odoo/addons/stock_valuation_layer_inventory_filter/models/__init__.py
odoo/addons/stock_valuation_layer_inventory_filter/models/stock_valuation_layer.py
odoo/addons/stock_valuation_layer_inventory_filter/readme/CONTEXT.md
odoo/addons/stock_valuation_layer_inventory_filter/readme/CONTRIBUTORS.md
odoo/addons/stock_valuation_layer_inventory_filter/readme/DESCRIPTION.md
odoo/addons/stock_valuation_layer_inventory_filter/readme/USAGE.md
odoo/addons/stock_valuation_layer_inventory_filter/static/description/icon.png
odoo/addons/stock_valuation_layer_inventory_filter/static/description/index.html
odoo/addons/stock_valuation_layer_inventory_filter/views/stock_valuation_layer_view.xml
odoo_addon_stock_valuation_layer_inventory_filter-18.0.1.0.1.dist-info/METADATA
odoo_addon_stock_valuation_layer_inventory_filter-18.0.1.0.1.dist-info/WHEEL
odoo_addon_stock_valuation_layer_inventory_filter-18.0.1.0.1.dist-info/top_level.txt
odoo_addon_stock_valuation_layer_inventory_filter-18.0.1.0.1.dist-info/RECORD
